{"subjects":[{"uri":"jbr:mishna","jbo:within":"משנה"},{"uri":"jbr:mishna-1","rdfs:label":"סדר זרעים","jbo:within":"jbr:mishna-1","jbo:position":"1"},{"uri":"jbr:mishna-1-2","rdfs:label":"﻿משנה מסכת פאה","jbo:within":"jbr:mishna-1","jbo:within":"jbr:mishna-1-2","jbo:position":"2"},{"uri":"jbr:mishna-1-2-1","rdfs:label":"משנה פאה פרק א","jbo:within":"jbr:mishna-1","jbo:within":"jbr:mishna-1-2","jbo:within":"jbr:mishna-1-2-1","jbo:position":"1"},{"uri":"jbr:mishna-1-2-2","rdfs:label":"משנה פאה פרק ב","jbo:within":"jbr:mishna-1","jbo:within":"jbr:mishna-1-2","jbo:within":"jbr:mishna-1-2-2","jbo:position":"2"},{"uri":"jbr:mishna-1-2-3","rdfs:label":"משנה פאה פרק ג","jbo:within":"jbr:mishna-1","jbo:within":"jbr:mishna-1-2","jbo:within":"jbr:mishna-1-2-3","jbo:position":"3"},{"uri":"jbr:mishna-1-2-4","rdfs:label":"משנה פאה פרק ד","jbo:within":"jbr:mishna-1","jbo:within":"jbr:mishna-1-2","jbo:within":"jbr:mishna-1-2-4","jbo:position":"4"},{"uri":"jbr:mishna-1-2-5","rdfs:label":"משנה פאה פרק ה","jbo:within":"jbr:mishna-1","jbo:within":"jbr:mishna-1-2","jbo:within":"jbr:mishna-1-2-5","jbo:position":"5"},{"uri":"jbr:mishna-1-2-6","rdfs:label":"משנה פאה פרק ו","jbo:within":"jbr:mishna-1","jbo:within":"jbr:mishna-1-2","jbo:within":"jbr:mishna-1-2-6","jbo:position":"6"},{"uri":"jbr:mishna-1-2-7","rdfs:label":"משנה פאה פרק ז","jbo:within":"jbr:mishna-1","jbo:within":"jbr:mishna-1-2","jbo:within":"jbr:mishna-1-2-7","jbo:position":"7"},{"uri":"jbr:mishna-1-2-8","rdfs:label":"משנה פאה פרק ח","jbo:within":"jbr:mishna-1","jbo:within":"jbr:mishna-1-2","jbo:within":"jbr:mishna-1-2-8","jbo:position":"8"}]}