{"subjects":[{"uri":"jbr:mishna","jbo:within":"משנה"},{"uri":"jbr:mishna-5","rdfs:label":"סדר קדשים","jbo:within":"jbr:mishna-5","jbo:position":"5"},{"uri":"jbr:mishna-5-9","rdfs:label":"﻿משנה מסכת תמיד","jbo:within":"jbr:mishna-5","jbo:within":"jbr:mishna-5-9","jbo:position":"9"},{"uri":"jbr:mishna-5-9-1","rdfs:label":"משנה תמיד פרק א","jbo:within":"jbr:mishna-5","jbo:within":"jbr:mishna-5-9","jbo:within":"jbr:mishna-5-9-1","jbo:position":"1"},{"uri":"jbr:mishna-5-9-2","rdfs:label":"משנה תמיד פרק ב","jbo:within":"jbr:mishna-5","jbo:within":"jbr:mishna-5-9","jbo:within":"jbr:mishna-5-9-2","jbo:position":"2"},{"uri":"jbr:mishna-5-9-3","rdfs:label":"משנה תמיד פרק ג","jbo:within":"jbr:mishna-5","jbo:within":"jbr:mishna-5-9","jbo:within":"jbr:mishna-5-9-3","jbo:position":"3"},{"uri":"jbr:mishna-5-9-4","rdfs:label":"משנה תמיד פרק ד","jbo:within":"jbr:mishna-5","jbo:within":"jbr:mishna-5-9","jbo:within":"jbr:mishna-5-9-4","jbo:position":"4"},{"uri":"jbr:mishna-5-9-5","rdfs:label":"משנה תמיד פרק ה","jbo:within":"jbr:mishna-5","jbo:within":"jbr:mishna-5-9","jbo:within":"jbr:mishna-5-9-5","jbo:position":"5"},{"uri":"jbr:mishna-5-9-6","rdfs:label":"משנה תמיד פרק ו","jbo:within":"jbr:mishna-5","jbo:within":"jbr:mishna-5-9","jbo:within":"jbr:mishna-5-9-6","jbo:position":"6"},{"uri":"jbr:mishna-5-9-7","rdfs:label":"משנה תמיד פרק ז","jbo:within":"jbr:mishna-5","jbo:within":"jbr:mishna-5-9","jbo:within":"jbr:mishna-5-9-7","jbo:position":"7"}]}