{"subjects":[{"uri":"tanach--metzudattzion18-1-1","text":" מצודת ציון  וציר. ענין שליח כמו וציר אמונים (משלי יג) ","titles":[{"title":"עובדיה א א"},{"title":"עובדיה פרק א פסוק א"}]},{"sefer":"tanach-18"},{"parasha":"parasha-1"},{"perek":"tanach-18-1"},{"positionInPerek":1},{"positionInParasha":1},{"uri":"tanach--metzudattzion18-1-2","text":" מצודת ציון  בזוי. מבוזה ","titles":[{"title":"עובדיה א ב"},{"title":"עובדיה פרק א פסוק ב"}]},{"sefer":"tanach-18"},{"parasha":"parasha-1"},{"perek":"tanach-18-1"},{"positionInPerek":2},{"positionInParasha":2},{"uri":"tanach--metzudattzion18-1-3","text":" מצודת ציון  השיאך. ענין הסתה כמו הנחש השיאני (בראשית ג) ","titles":[{"title":"עובדיה א ג"},{"title":"עובדיה פרק א פסוק ג"}]},{"sefer":"tanach-18"},{"parasha":"parasha-1"},{"perek":"tanach-18-1"},{"positionInPerek":3},{"positionInParasha":3},{"uri":"tanach--metzudattzion18-1-4","text":" מצודת ציון  קנך. מל' קן והוא מדור העופות ","titles":[{"title":"עובדיה א ד"},{"title":"עובדיה פרק א פסוק ד"}]},{"sefer":"tanach-18"},{"parasha":"parasha-1"},{"perek":"tanach-18-1"},{"positionInPerek":4},{"positionInParasha":4},{"uri":"tanach--metzudattzion18-1-5","text":" מצודת ציון  שודדי. ענין גזל ועושק ","titles":[{"title":"עובדיה א ה"},{"title":"עובדיה פרק א פסוק ה"}]},{"sefer":"tanach-18"},{"parasha":"parasha-1"},{"perek":"tanach-18-1"},{"positionInPerek":5},{"positionInParasha":5},{"uri":"tanach--metzudattzion18-1-6","text":" מצודת ציון  נחפשו. מלשון חפוש וחקירה כמו משם אחפש (עמוס ט) ","titles":[{"title":"עובדיה א ו"},{"title":"עובדיה פרק א פסוק ו"}]},{"sefer":"tanach-18"},{"parasha":"parasha-1"},{"perek":"tanach-18-1"},{"positionInPerek":6},{"positionInParasha":6},{"uri":"tanach--metzudattzion18-1-7","text":" מצודת ציון  שלחוך. ענין לויה כמו ואברה' הולך עמם לשלחם (בראשי' יח) ","titles":[{"title":"עובדיה א ז"},{"title":"עובדיה פרק א פסוק ז"}]},{"sefer":"tanach-18"},{"parasha":"parasha-1"},{"perek":"tanach-18-1"},{"positionInPerek":7},{"positionInParasha":7},{"uri":"tanach--metzudattzion18-1-9","text":" מצודת ציון  וחתו. ענין שבירה כמו והחתתי את עילם (ירמיה מט) ","titles":[{"title":"עובדיה א ט"},{"title":"עובדיה פרק א פסוק ט"}]},{"sefer":"tanach-18"},{"parasha":"parasha-1"},{"perek":"tanach-18-1"},{"positionInPerek":9},{"positionInParasha":9},{"uri":"tanach--metzudattzion18-1-10","text":" מצודת ציון  מחמס. ענין עושק ","titles":[{"title":"עובדיה א י"},{"title":"עובדיה פרק א פסוק י"}]},{"sefer":"tanach-18"},{"parasha":"parasha-1"},{"perek":"tanach-18-1"},{"positionInPerek":10},{"positionInParasha":10},{"uri":"tanach--metzudattzion18-1-11","text":" מצודת ציון  מנגד. ממרחק ","titles":[{"title":"עובדיה א יא"},{"title":"עובדיה פרק א פסוק יא"}]},{"sefer":"tanach-18"},{"parasha":"parasha-1"},{"perek":"tanach-18-1"},{"positionInPerek":11},{"positionInParasha":11},{"uri":"tanach--metzudattzion18-1-12","text":" מצודת ציון  נכרו. מל' נכר וזר ","titles":[{"title":"עובדיה א יב"},{"title":"עובדיה פרק א פסוק יב"}]},{"sefer":"tanach-18"},{"parasha":"parasha-1"},{"perek":"tanach-18-1"},{"positionInPerek":12},{"positionInParasha":12},{"uri":"tanach--metzudattzion18-1-13","text":" מצודת ציון  אידם. ענין צער ומקרה רע כמו הלא איד לעול (איוב לא) ","titles":[{"title":"עובדיה א יג"},{"title":"עובדיה פרק א פסוק יג"}]},{"sefer":"tanach-18"},{"parasha":"parasha-1"},{"perek":"tanach-18-1"},{"positionInPerek":13},{"positionInParasha":13},{"uri":"tanach--metzudattzion18-1-14","text":" מצודת ציון  תעמוד. ענינו התחזקות על הדבר וההשתדלות עליו ודומה לו אך יונתן וגו' עמדו על זאת (עזרא י) ","titles":[{"title":"עובדיה א יד"},{"title":"עובדיה פרק א פסוק יד"}]},{"sefer":"tanach-18"},{"parasha":"parasha-1"},{"perek":"tanach-18-1"},{"positionInPerek":14},{"positionInParasha":14},{"uri":"tanach--metzudattzion18-1-15","text":" מצודת ציון  קרוב. ר''ל נכון ומזומן לפניו וכן כי קרוב יום אידם (דברים לב) ","titles":[{"title":"עובדיה א טו"},{"title":"עובדיה פרק א פסוק טו"}]},{"sefer":"tanach-18"},{"parasha":"parasha-1"},{"perek":"tanach-18-1"},{"positionInPerek":15},{"positionInParasha":15},{"uri":"tanach--metzudattzion18-1-16","text":" מצודת ציון  ולעו. ענין השחתה ובלבול וכן על כן דברי לעו (איוב ו) ","titles":[{"title":"עובדיה א טז"},{"title":"עובדיה פרק א פסוק טז"}]},{"sefer":"tanach-18"},{"parasha":"parasha-1"},{"perek":"tanach-18-1"},{"positionInPerek":16},{"positionInParasha":16},{"uri":"tanach--metzudattzion18-1-17","text":" מצודת ציון  מורשיהם. מל' ירושה ","titles":[{"title":"עובדיה א יז"},{"title":"עובדיה פרק א פסוק יז"}]},{"sefer":"tanach-18"},{"parasha":"parasha-1"},{"perek":"tanach-18-1"},{"positionInPerek":17},{"positionInParasha":17},{"uri":"tanach--metzudattzion18-1-18","text":" מצודת ציון  להבה. שלהבת ","titles":[{"title":"עובדיה א יח"},{"title":"עובדיה פרק א פסוק יח"}]},{"sefer":"tanach-18"},{"parasha":"parasha-1"},{"perek":"tanach-18-1"},{"positionInPerek":18},{"positionInParasha":18},{"uri":"tanach--metzudattzion18-1-19","text":" מצודת ציון  והשפלה. העמק ","titles":[{"title":"עובדיה א יט"},{"title":"עובדיה פרק א פסוק יט"}]},{"sefer":"tanach-18"},{"parasha":"parasha-1"},{"perek":"tanach-18-1"},{"positionInPerek":19},{"positionInParasha":19},{"uri":"tanach--metzudattzion18-1-20","text":" מצודת ציון  החל. כמו החיל ונפלה היו''ד ","titles":[{"title":"עובדיה א כ"},{"title":"עובדיה פרק א פסוק כ"}]},{"sefer":"tanach-18"},{"parasha":"parasha-1"},{"perek":"tanach-18-1"},{"positionInPerek":20},{"positionInParasha":20}]}