{"subjects":[{"uri":"tanach-metzudattzion-37-1-1","text":" מצודת ציון  הבירה. ר''ל מקום ארמון המלך ","titles":[{"title":"נחמיה א א"},{"title":"נחמיה פרק א פסוק א"}],"sefer":"tanach-37","parasha":"parasha-1","perek":"tanach-37-1","positionInPerek":1,"positionInParasha":1},{"uri":"tanach-metzudattzion-37-1-2","text":" מצודת ציון  הפליטה. ענין שארית וכן שריד ופליט (יהושע ח') ","titles":[{"title":"נחמיה א ב"},{"title":"נחמיה פרק א פסוק ב"}],"sefer":"tanach-37","parasha":"parasha-1","perek":"tanach-37-1","positionInPerek":2,"positionInParasha":2},{"uri":"tanach-metzudattzion-37-1-3","text":" מצודת ציון  מפורצת. מל' פרצה ושבר ","titles":[{"title":"נחמיה א ג"},{"title":"נחמיה פרק א פסוק ג"}],"sefer":"tanach-37","parasha":"parasha-1","perek":"tanach-37-1","positionInPerek":3,"positionInParasha":3},{"uri":"tanach-metzudattzion-37-1-4","text":" מצודת ציון  צם. מתענה ","titles":[{"title":"נחמיה א ד"},{"title":"נחמיה פרק א פסוק ד"}],"sefer":"tanach-37","parasha":"parasha-1","perek":"tanach-37-1","positionInPerek":4,"positionInParasha":4},{"uri":"tanach-metzudattzion-37-1-5","text":" מצודת ציון  אנא. הוא ענין ל' בקשה ","titles":[{"title":"נחמיה א ה"},{"title":"נחמיה פרק א פסוק ה"}],"sefer":"tanach-37","parasha":"parasha-1","perek":"tanach-37-1","positionInPerek":5,"positionInParasha":5},{"uri":"tanach-metzudattzion-37-1-6","text":" מצודת ציון  תהי נא. תהא עתה או היא ענין ל' בקשה ","titles":[{"title":"נחמיה א ו"},{"title":"נחמיה פרק א פסוק ו"}],"sefer":"tanach-37","parasha":"parasha-1","perek":"tanach-37-1","positionInPerek":6,"positionInParasha":6},{"uri":"tanach-metzudattzion-37-1-7","text":" מצודת ציון  חבול. ענין השחתה כי השחית כל בשר (בראשית ו') ת''א חבילו ","titles":[{"title":"נחמיה א ז"},{"title":"נחמיה פרק א פסוק ז"}],"sefer":"tanach-37","parasha":"parasha-1","perek":"tanach-37-1","positionInPerek":7,"positionInParasha":7},{"uri":"tanach-metzudattzion-37-1-8","text":" מצודת ציון  תמעלו. ענין חטא ופשע ","titles":[{"title":"נחמיה א ח"},{"title":"נחמיה פרק א פסוק ח"}],"sefer":"tanach-37","parasha":"parasha-1","perek":"tanach-37-1","positionInPerek":8,"positionInParasha":8},{"uri":"tanach-metzudattzion-37-2-1","text":" מצודת ציון  לארתחשסתא. הוא דריוש הפרסי ונקרא כן ע''ש המלכות כמו פרעה למצרים והדומים ","titles":[{"title":"נחמיה ב א"},{"title":"נחמיה פרק ב פסוק א"}],"sefer":"tanach-37","parasha":"parasha-1","perek":"tanach-37-2","positionInPerek":1,"positionInParasha":11},{"uri":"tanach-metzudattzion-37-2-3","text":" מצודת ציון  ירעו. מל' רעה ","titles":[{"title":"נחמיה ב ג"},{"title":"נחמיה פרק ב פסוק ג"}],"sefer":"tanach-37","parasha":"parasha-1","perek":"tanach-37-2","positionInPerek":3,"positionInParasha":13},{"uri":"tanach-metzudattzion-37-2-6","text":" מצודת ציון  והשגל. המלכה המיוחדת לו למשכב המשגל ","titles":[{"title":"נחמיה ב ו"},{"title":"נחמיה פרק ב פסוק ו"}],"sefer":"tanach-37","parasha":"parasha-1","perek":"tanach-37-2","positionInPerek":6,"positionInParasha":16},{"uri":"tanach-metzudattzion-37-2-8","text":" מצודת ציון  הפרדס. הוא גן מעץ פרי כמו גנות ופרדסים (קהלת ב') ","titles":[{"title":"נחמיה ב ח"},{"title":"נחמיה פרק ב פסוק ח"}],"sefer":"tanach-37","parasha":"parasha-1","perek":"tanach-37-2","positionInPerek":8,"positionInParasha":18},{"uri":"tanach-metzudattzion-37-2-12","text":" מצודת ציון  רוכב בה. רוכב עליה וכן ינתן בו (שמות כ''א) ור''ל עליו ","titles":[{"title":"נחמיה ב יב"},{"title":"נחמיה פרק ב פסוק יב"}],"sefer":"tanach-37","parasha":"parasha-1","perek":"tanach-37-2","positionInPerek":12,"positionInParasha":22},{"uri":"tanach-metzudattzion-37-2-13","text":" מצודת ציון  אכלו. נשרפו ","titles":[{"title":"נחמיה ב יג"},{"title":"נחמיה פרק ב פסוק יג"}],"sefer":"tanach-37","parasha":"parasha-1","perek":"tanach-37-2","positionInPerek":13,"positionInParasha":23},{"uri":"tanach-metzudattzion-37-2-14","text":" מצודת ציון  ברכת. ענין מקוה המים וכן תעלת הברכה (ישעיה ז') ","titles":[{"title":"נחמיה ב יד"},{"title":"נחמיה פרק ב פסוק יד"}],"sefer":"tanach-37","parasha":"parasha-1","perek":"tanach-37-2","positionInPerek":14,"positionInParasha":24},{"uri":"tanach-metzudattzion-37-2-15","text":" מצודת ציון  בנחל. בעמק ואמר עולה כי לפני הנחל היה הר ","titles":[{"title":"נחמיה ב טו"},{"title":"נחמיה פרק ב פסוק טו"}],"sefer":"tanach-37","parasha":"parasha-1","perek":"tanach-37-2","positionInPerek":15,"positionInParasha":25},{"uri":"tanach-metzudattzion-37-2-16","text":" מצודת ציון  והסגנים. הוא מין שררה ","titles":[{"title":"נחמיה ב טז"},{"title":"נחמיה פרק ב פסוק טז"}],"sefer":"tanach-37","parasha":"parasha-1","perek":"tanach-37-2","positionInPerek":16,"positionInParasha":26},{"uri":"tanach-metzudattzion-37-2-17","text":" מצודת ציון  נצתו. מל' הצתה ושריפה ","titles":[{"title":"נחמיה ב יז"},{"title":"נחמיה פרק ב פסוק יז"}],"sefer":"tanach-37","parasha":"parasha-1","perek":"tanach-37-2","positionInPerek":17,"positionInParasha":27},{"uri":"tanach-metzudattzion-37-3-1","text":" מצודת ציון  שער הצאן. כן שמו על דבר ידוע אצלם וכן כולם ","titles":[{"title":"נחמיה ג א"},{"title":"נחמיה פרק ג פסוק א"}],"sefer":"tanach-37","parasha":"parasha-1","perek":"tanach-37-3","positionInPerek":1,"positionInParasha":31},{"uri":"tanach-metzudattzion-37-3-5","text":" מצודת ציון  ואדיריהם. מל' אדיר וחזק ור''ל העשירים ","titles":[{"title":"נחמיה ג ה"},{"title":"נחמיה פרק ג פסוק ה"}],"sefer":"tanach-37","parasha":"parasha-1","perek":"tanach-37-3","positionInPerek":5,"positionInParasha":35},{"uri":"tanach-metzudattzion-37-3-7","text":" מצודת ציון  פחת. ענין שררה ומושל ","titles":[{"title":"נחמיה ג ז"},{"title":"נחמיה פרק ג פסוק ז"}],"sefer":"tanach-37","parasha":"parasha-1","perek":"tanach-37-3","positionInPerek":7,"positionInParasha":37},{"uri":"tanach-metzudattzion-37-3-8","text":" מצודת ציון  צורפים. צורפי זהב וכסף ","titles":[{"title":"נחמיה ג ח"},{"title":"נחמיה פרק ג פסוק ח"}],"sefer":"tanach-37","parasha":"parasha-1","perek":"tanach-37-3","positionInPerek":8,"positionInParasha":38},{"uri":"tanach-metzudattzion-37-3-9","text":" מצודת ציון  פלך. מחוז כי חבל ארגוב (דברים ג') ת''א בית פלך ","titles":[{"title":"נחמיה ג ט"},{"title":"נחמיה פרק ג פסוק ט"}],"sefer":"tanach-37","parasha":"parasha-1","perek":"tanach-37-3","positionInPerek":9,"positionInParasha":39},{"uri":"tanach-metzudattzion-37-3-13","text":" מצודת ציון  השפות. כמו האשפות ","titles":[{"title":"נחמיה ג יג"},{"title":"נחמיה פרק ג פסוק יג"}],"sefer":"tanach-37","parasha":"parasha-1","perek":"tanach-37-3","positionInPerek":13,"positionInParasha":43},{"uri":"tanach-metzudattzion-37-3-15","text":" מצודת ציון  ויטללנו. הוא ענין צל כי בצל קורתי (בראשית י''ט) ת''א בטלל ור''ל עשה חקרה לצל ומחסה ","titles":[{"title":"נחמיה ג טו"},{"title":"נחמיה פרק ג פסוק טו"}],"sefer":"tanach-37","parasha":"parasha-1","perek":"tanach-37-3","positionInPerek":15,"positionInParasha":45},{"uri":"tanach-metzudattzion-37-3-19","text":" מצודת ציון  הנשק. כלי זיין כמו ועיר מבצר והנשק (מ''ב י') ","titles":[{"title":"נחמיה ג יט"},{"title":"נחמיה פרק ג פסוק יט"}],"sefer":"tanach-37","parasha":"parasha-1","perek":"tanach-37-3","positionInPerek":19,"positionInParasha":49},{"uri":"tanach-metzudattzion-37-3-20","text":" מצודת ציון  החרה. ענין חמום כמו נחר מפוח (ירמיה ו') ","titles":[{"title":"נחמיה ג כ"},{"title":"נחמיה פרק ג פסוק כ"}],"sefer":"tanach-37","parasha":"parasha-1","perek":"tanach-37-3","positionInPerek":20,"positionInParasha":50},{"uri":"tanach-metzudattzion-37-3-21","text":" מצודת ציון  תכלית. קצה וסוף ","titles":[{"title":"נחמיה ג כא"},{"title":"נחמיה פרק ג פסוק כא"}],"sefer":"tanach-37","parasha":"parasha-1","perek":"tanach-37-3","positionInPerek":21,"positionInParasha":51},{"uri":"tanach-metzudattzion-37-3-23","text":" מצודת ציון  הפנה. כן נקרא המגדל על כי דרכו לעמוד בפנה וכן ועל הפנות הגבוהות (צפניה א') ","titles":[{"title":"נחמיה ג כד"},{"title":"נחמיה פרק ג פסוק כד"}],"sefer":"tanach-37","parasha":"parasha-1","perek":"tanach-37-3","positionInPerek":23,"positionInParasha":53},{"uri":"tanach-metzudattzion-37-3-24","text":" מצודת ציון  המטרה. הוא משמר בית האסורים כי ויאסוף אותם אל משמר (בראשית מ''ב) ת''א לבית מטרה ","titles":[{"title":"נחמיה ג כה"},{"title":"נחמיה פרק ג פסוק כה"}],"sefer":"tanach-37","parasha":"parasha-1","perek":"tanach-37-3","positionInPerek":24,"positionInParasha":54},{"uri":"tanach-metzudattzion-37-3-25","text":" מצודת ציון  והנתינים. הם הגבעונים ","titles":[{"title":"נחמיה ג כו"},{"title":"נחמיה פרק ג פסוק כו"}],"sefer":"tanach-37","parasha":"parasha-1","perek":"tanach-37-3","positionInPerek":25,"positionInParasha":55},{"uri":"tanach-metzudattzion-37-3-30","text":" מצודת ציון  והרוכלים. הם סוחרי הבושם ","titles":[{"title":"נחמיה ג לא"},{"title":"נחמיה פרק ג פסוק לא"}],"sefer":"tanach-37","parasha":"parasha-1","perek":"tanach-37-3","positionInPerek":30,"positionInParasha":60},{"uri":"tanach-metzudattzion-37-3-33","text":" מצודת ציון  האמללים. הנכרתים וחלושים כמו כי אומלל אני (תהלים ו') ","titles":[{"title":"נחמיה ג לד"},{"title":"נחמיה פרק ג פסוק לד"}],"sefer":"tanach-37","parasha":"parasha-1","perek":"tanach-37-3","positionInPerek":33,"positionInParasha":63},{"uri":"tanach-metzudattzion-37-3-36","text":" מצודת ציון  תכס. כמו תכסה ","titles":[{"title":"נחמיה ג לז"},{"title":"נחמיה פרק ג פסוק לז"}],"sefer":"tanach-37","parasha":"parasha-1","perek":"tanach-37-3","positionInPerek":36,"positionInParasha":66},{"uri":"tanach-metzudattzion-37-4-1","text":" מצודת ציון  ארוכה. ענין רפואה כמו ארוכת בת עמי (ירמיה ח') ור''ל נתחזק ובא בדרך השאלה ","titles":[{"title":"נחמיה ד א"},{"title":"נחמיה פרק ד פסוק א"}],"sefer":"tanach-37","parasha":"parasha-1","perek":"tanach-37-4","positionInPerek":1,"positionInParasha":68},{"uri":"tanach-metzudattzion-37-4-2","text":" מצודת ציון  ויקשרו. ענין אגודה ","titles":[{"title":"נחמיה ד ב"},{"title":"נחמיה פרק ד פסוק ב"}],"sefer":"tanach-37","parasha":"parasha-1","perek":"tanach-37-4","positionInPerek":2,"positionInParasha":69},{"uri":"tanach-metzudattzion-37-4-4","text":" מצודת ציון  כשל. ענין חלשות ונפילת הכח כמו לכל כושל (דה''ב כ''ח) ","titles":[{"title":"נחמיה ד ד"},{"title":"נחמיה פרק ד פסוק ד"}],"sefer":"tanach-37","parasha":"parasha-1","perek":"tanach-37-4","positionInPerek":4,"positionInParasha":71},{"uri":"tanach-metzudattzion-37-4-5","text":" מצודת ציון  והשבתנו. ענין בטול ומניעה כמו שבת נוגש (ישעיה י''ד) ","titles":[{"title":"נחמיה ד ה"},{"title":"נחמיה פרק ד פסוק ה"}],"sefer":"tanach-37","parasha":"parasha-1","perek":"tanach-37-4","positionInPerek":5,"positionInParasha":72},{"uri":"tanach-metzudattzion-37-4-7","text":" מצודת ציון  בצחיחים. בעליונות הסלעים מקום היובש שבו והוא מלשון צחה צמא (שם ה') וכן על צחיח סלע (יחזקאל כ''ד) ","titles":[{"title":"נחמיה ד ז"},{"title":"נחמיה פרק ד פסוק ז"}],"sefer":"tanach-37","parasha":"parasha-1","perek":"tanach-37-4","positionInPerek":7,"positionInParasha":74},{"uri":"tanach-metzudattzion-37-4-10","text":" מצודת ציון  והרמחים. הוי''ו יתירה ","titles":[{"title":"נחמיה ד י"},{"title":"נחמיה פרק ד פסוק י"}],"sefer":"tanach-37","parasha":"parasha-1","perek":"tanach-37-4","positionInPerek":10,"positionInParasha":77},{"uri":"tanach-metzudattzion-37-4-11","text":" מצודת ציון  עומשים. כמו עומסים בסמ''ך והוא ענין טעינת משא כמו ויעמוס איש על חמורו (בראשית מ''ד) ","titles":[{"title":"נחמיה ד יא"},{"title":"נחמיה פרק ד פסוק יא"}],"sefer":"tanach-37","parasha":"parasha-1","perek":"tanach-37-4","positionInPerek":11,"positionInParasha":78},{"uri":"tanach-metzudattzion-37-4-12","text":" מצודת ציון  אסורים. קשורים ","titles":[{"title":"נחמיה ד יב"},{"title":"נחמיה פרק ד פסוק יב"}],"sefer":"tanach-37","parasha":"parasha-1","perek":"tanach-37-4","positionInPerek":12,"positionInParasha":79},{"uri":"tanach-metzudattzion-37-4-13","text":" מצודת ציון  נפרדים. פזורים ","titles":[{"title":"נחמיה ד יג"},{"title":"נחמיה פרק ד פסוק יג"}],"sefer":"tanach-37","parasha":"parasha-1","perek":"tanach-37-4","positionInPerek":13,"positionInParasha":80},{"uri":"tanach-metzudattzion-37-4-15","text":" מצודת ציון  השחר. הוא האור הנוצץ בפאת המזרח טרם יגלה השמש ","titles":[{"title":"נחמיה ד טו"},{"title":"נחמיה פרק ד פסוק טו"}],"sefer":"tanach-37","parasha":"parasha-1","perek":"tanach-37-4","positionInPerek":15,"positionInParasha":82},{"uri":"tanach-metzudattzion-37-4-17","text":" מצודת ציון  שלחו. ענין הפשט כי ופשט את בגדיו (ויקרא ו) ת''א ושלח ","titles":[{"title":"נחמיה ד יז"},{"title":"נחמיה פרק ד פסוק יז"}],"sefer":"tanach-37","parasha":"parasha-1","perek":"tanach-37-4","positionInPerek":17,"positionInParasha":84},{"uri":"tanach-metzudattzion-37-5-3","text":" מצודת ציון  עורבים. ענין משכון כמו מה הערבון (בראשית לח) ","titles":[{"title":"נחמיה ה ג"},{"title":"נחמיה פרק ה פסוק ג"}],"sefer":"tanach-37","parasha":"parasha-1","perek":"tanach-37-5","positionInPerek":3,"positionInParasha":87},{"uri":"tanach-metzudattzion-37-5-4","text":" מצודת ציון  למדת. כמו למנדת והוא מין מס כמו מנדה בלו והלך (עזרא ד') ונפלה הנו''ן ","titles":[{"title":"נחמיה ה ד"},{"title":"נחמיה פרק ה פסוק ד"}],"sefer":"tanach-37","parasha":"parasha-1","perek":"tanach-37-5","positionInPerek":4,"positionInParasha":88},{"uri":"tanach-metzudattzion-37-5-5","text":" מצודת ציון  כובשים. ענין התפישה בחזקה כמו ויכבשום לעבדים (ירמיה לד) ","titles":[{"title":"נחמיה ה ה"},{"title":"נחמיה פרק ה פסוק ה"}],"sefer":"tanach-37","parasha":"parasha-1","perek":"tanach-37-5","positionInPerek":5,"positionInParasha":89},{"uri":"tanach-metzudattzion-37-5-6","text":" מצודת ציון  וימלך. ענין עצה כמו מלכי ישפר עליך (דניאל ד) ","titles":[{"title":"נחמיה ה ו"},{"title":"נחמיה פרק ה פסוק ו"}],"sefer":"tanach-37","parasha":"parasha-1","perek":"tanach-37-5","positionInPerek":6,"positionInParasha":90},{"uri":"tanach-metzudattzion-37-5-7","text":" מצודת ציון  כדי. מלשון די הפסוק ","titles":[{"title":"נחמיה ה ח"},{"title":"נחמיה פרק ה פסוק ח"}],"sefer":"tanach-37","parasha":"parasha-1","perek":"tanach-37-5","positionInPerek":7,"positionInParasha":91},{"uri":"tanach-metzudattzion-37-5-10","text":" מצודת ציון  ומאת הכסף. שקלי הכסף ","titles":[{"title":"נחמיה ה יא"},{"title":"נחמיה פרק ה פסוק יא"}],"sefer":"tanach-37","parasha":"parasha-1","perek":"tanach-37-5","positionInPerek":10,"positionInParasha":94},{"uri":"tanach-metzudattzion-37-5-12","text":" מצודת ציון  חצני. כן יקרא כנף הבגד וכן והביאו בניך בחוצן (ישעיה מ''ט) ","titles":[{"title":"נחמיה ה יג"},{"title":"נחמיה פרק ה פסוק יג"}],"sefer":"tanach-37","parasha":"parasha-1","perek":"tanach-37-5","positionInPerek":12,"positionInParasha":96},{"uri":"tanach-metzudattzion-37-5-13","text":" מצודת ציון  פחם. פחה שלהם ","titles":[{"title":"נחמיה ה יד"},{"title":"נחמיה פרק ה פסוק יד"}],"sefer":"tanach-37","parasha":"parasha-1","perek":"tanach-37-5","positionInPerek":13,"positionInParasha":97},{"uri":"tanach-metzudattzion-37-5-14","text":" מצודת ציון  אחר. הוא כענין מלבד ר''ל לבד לקיחת מ' שקלים לקחו עוד בלחם ויין ","titles":[{"title":"נחמיה ה טו"},{"title":"נחמיה פרק ה פסוק טו"}],"sefer":"tanach-37","parasha":"parasha-1","perek":"tanach-37-5","positionInPerek":14,"positionInParasha":98},{"uri":"tanach-metzudattzion-37-5-17","text":" מצודת ציון  נעשה. ענין תקון כמו וימהר לעשות אותו (בראשית י''ח) ","titles":[{"title":"נחמיה ה יח"},{"title":"נחמיה פרק ה פסוק יח"}],"sefer":"tanach-37","parasha":"parasha-1","perek":"tanach-37-5","positionInPerek":17,"positionInParasha":101},{"uri":"tanach-metzudattzion-37-6-1","text":" מצודת ציון  פרץ. שבירה ","titles":[{"title":"נחמיה ו א"},{"title":"נחמיה פרק ו פסוק א"}],"sefer":"tanach-37","parasha":"parasha-1","perek":"tanach-37-6","positionInPerek":1,"positionInParasha":103},{"uri":"tanach-metzudattzion-37-6-2","text":" מצודת ציון  ונועדה. מל' וועד ואסיפה כמו ויועדו כל המלכים (יהושע י''א) ","titles":[{"title":"נחמיה ו ב"},{"title":"נחמיה פרק ו פסוק ב"}],"sefer":"tanach-37","parasha":"parasha-1","perek":"tanach-37-6","positionInPerek":2,"positionInParasha":104},{"uri":"tanach-metzudattzion-37-6-3","text":" מצודת ציון  תשבת. מלשון השבתה ובטול ","titles":[{"title":"נחמיה ו ג"},{"title":"נחמיה פרק ו פסוק ג"}],"sefer":"tanach-37","parasha":"parasha-1","perek":"tanach-37-6","positionInPerek":3,"positionInParasha":105},{"uri":"tanach-metzudattzion-37-6-6","text":" מצודת ציון  וגשמו. הוא גשם הערבי וכן יתר יתרו ","titles":[{"title":"נחמיה ו ו"},{"title":"נחמיה פרק ו פסוק ו"}],"sefer":"tanach-37","parasha":"parasha-1","perek":"tanach-37-6","positionInPerek":6,"positionInParasha":108},{"uri":"tanach-metzudattzion-37-6-7","text":" מצודת ציון  נביאים. ענינו בעלי הדבור כמו ניב שפתים (ישעיה נ''ז) ","titles":[{"title":"נחמיה ו ז"},{"title":"נחמיה פרק ו פסוק ז"}],"sefer":"tanach-37","parasha":"parasha-1","perek":"tanach-37-6","positionInPerek":7,"positionInParasha":109},{"uri":"tanach-metzudattzion-37-6-8","text":" מצודת ציון  בודם. ענין המצאת הכזב וכן בדיך מתים יחרישו (איוב י''א) ","titles":[{"title":"נחמיה ו ח"},{"title":"נחמיה פרק ו פסוק ח"}],"sefer":"tanach-37","parasha":"parasha-1","perek":"tanach-37-6","positionInPerek":8,"positionInParasha":110},{"uri":"tanach-metzudattzion-37-6-9","text":" מצודת ציון  כולם. ענינו כמו כולכם ודוגמתו ואולם כולם תשובו (שם י''ז) ","titles":[{"title":"נחמיה ו ט"},{"title":"נחמיה פרק ו פסוק ט"}],"sefer":"tanach-37","parasha":"parasha-1","perek":"tanach-37-6","positionInPerek":9,"positionInParasha":111},{"uri":"tanach-metzudattzion-37-6-10","text":" מצודת ציון  עצור. מעוכב וכן נעצרה נא אותך (שופטים י''ג) ","titles":[{"title":"נחמיה ו י"},{"title":"נחמיה פרק ו פסוק י"}],"sefer":"tanach-37","parasha":"parasha-1","perek":"tanach-37-6","positionInPerek":10,"positionInParasha":112},{"uri":"tanach-metzudattzion-37-6-12","text":" מצודת ציון  וסנבלט. הוי''ו היא במקום או כמו ומקלל אביו ואמו (שמות כ''א) ","titles":[{"title":"נחמיה ו יב"},{"title":"נחמיה פרק ו פסוק יב"}],"sefer":"tanach-37","parasha":"parasha-1","perek":"tanach-37-6","positionInPerek":12,"positionInParasha":114},{"uri":"tanach-metzudattzion-37-6-16","text":" מצודת ציון  ויפלו. ענינו שפלות וגרעון כמו נופלים מערלים (יחזקאל ל''ב) ","titles":[{"title":"נחמיה ו טז"},{"title":"נחמיה פרק ו פסוק טז"}],"sefer":"tanach-37","parasha":"parasha-1","perek":"tanach-37-6","positionInPerek":16,"positionInParasha":118},{"uri":"tanach-metzudattzion-37-7-1","text":" מצודת ציון  ויפקדו. מלשון פקידות וגזברות ","titles":[{"title":"נחמיה ז א"},{"title":"נחמיה פרק ז פסוק א"}],"sefer":"tanach-37","parasha":"parasha-1","perek":"tanach-37-7","positionInPerek":1,"positionInParasha":122},{"uri":"tanach-metzudattzion-37-7-3","text":" מצודת ציון  יגיפו. יסגירו כי וסגרת הדלת (מ''ב ד') ת''י ותגיפון ","titles":[{"title":"נחמיה ז ג"},{"title":"נחמיה פרק ז פסוק ג"}],"sefer":"tanach-37","parasha":"parasha-1","perek":"tanach-37-7","positionInPerek":3,"positionInParasha":124},{"uri":"tanach-metzudattzion-37-7-5","text":" מצודת ציון  להתייחש. ענין יחוס הוא הודעת ספר הדורות מן המשפחות ומי אביהם ","titles":[{"title":"נחמיה ז ה"},{"title":"נחמיה פרק ז פסוק ה"}],"sefer":"tanach-37","parasha":"parasha-1","perek":"tanach-37-7","positionInPerek":5,"positionInParasha":126},{"uri":"tanach-metzudattzion-37-7-21","text":" מצודת ציון  ויגאלו. ענין טנוף ומאוס וכן לחם מגואל (מלאכי א') ","titles":[{"title":"נחמיה ז סד"},{"title":"נחמיה פרק ז פסוק סד"}],"sefer":"tanach-37","parasha":"parasha-1","perek":"tanach-37-7","positionInPerek":21,"positionInParasha":142},{"uri":"tanach-metzudattzion-37-7-23","text":" מצודת ציון  רבוא. הוא עשרת אלפים ","titles":[{"title":"נחמיה ז סו"},{"title":"נחמיה פרק ז פסוק סו"}],"sefer":"tanach-37","parasha":"parasha-1","perek":"tanach-37-7","positionInPerek":23,"positionInParasha":144},{"uri":"tanach-metzudattzion-37-7-25","text":" מצודת ציון  פרדיהם. הם הבאים מן הסוס והחמור ","titles":[{"title":"נחמיה ז סח"},{"title":"נחמיה פרק ז פסוק סח"}],"sefer":"tanach-37","parasha":"parasha-1","perek":"tanach-37-7","positionInPerek":25,"positionInParasha":146},{"uri":"tanach-metzudattzion-37-7-26","text":" מצודת ציון  דרכמונים. שם מטבע ידוע אצלם ","titles":[{"title":"נחמיה ז סט"},{"title":"נחמיה פרק ז פסוק סט"}],"sefer":"tanach-37","parasha":"parasha-1","perek":"tanach-37-7","positionInPerek":26,"positionInParasha":147},{"uri":"tanach-metzudattzion-37-7-27","text":" מצודת ציון  מנים. שם משקל ליטרא ","titles":[{"title":"נחמיה ז עא"},{"title":"נחמיה פרק ז פסוק עא"}],"sefer":"tanach-37","parasha":"parasha-1","perek":"tanach-37-7","positionInPerek":27,"positionInParasha":148},{"uri":"tanach-metzudattzion-37-7-28","text":" מצודת ציון  ויגע. כמו והגיע ","titles":[{"title":"נחמיה ז עב"},{"title":"נחמיה פרק ז פסוק עב"}],"sefer":"tanach-37","parasha":"parasha-1","perek":"tanach-37-7","positionInPerek":28,"positionInParasha":149},{"uri":"tanach-metzudattzion-37-8-1","text":" מצודת ציון  הסופר. החכם ובדח''ל סופר מברך ובור יוצא (חולין קי''ח) ","titles":[{"title":"נחמיה ח א"},{"title":"נחמיה פרק ח פסוק א"}],"sefer":"tanach-37","parasha":"parasha-1","perek":"tanach-37-8","positionInPerek":1,"positionInParasha":150},{"uri":"tanach-metzudattzion-37-8-5","text":" מצודת ציון  עמדו. ענין שתיקה כמו עמדו ולא ענו (איוב ל''ב) ","titles":[{"title":"נחמיה ח ה"},{"title":"נחמיה פרק ח פסוק ה"}],"sefer":"tanach-37","parasha":"parasha-1","perek":"tanach-37-8","positionInPerek":5,"positionInParasha":154},{"uri":"tanach-metzudattzion-37-8-6","text":" מצודת ציון  במועל. מלשון העלאה והרמה ","titles":[{"title":"נחמיה ח ו"},{"title":"נחמיה פרק ח פסוק ו"}],"sefer":"tanach-37","parasha":"parasha-1","perek":"tanach-37-8","positionInPerek":6,"positionInParasha":155},{"uri":"tanach-metzudattzion-37-8-8","text":" מצודת ציון  ושום. מלשון שימה ","titles":[{"title":"נחמיה ח ח"},{"title":"נחמיה פרק ח פסוק ח"}],"sefer":"tanach-37","parasha":"parasha-1","perek":"tanach-37-8","positionInPerek":8,"positionInParasha":157},{"uri":"tanach-metzudattzion-37-8-10","text":" מצודת ציון  מנות. ענין חלק ומתן כמו והיה לך למנה (שמות כ''ט) ","titles":[{"title":"נחמיה ח י"},{"title":"נחמיה פרק ח פסוק י"}],"sefer":"tanach-37","parasha":"parasha-1","perek":"tanach-37-8","positionInPerek":10,"positionInParasha":159},{"uri":"tanach-metzudattzion-37-8-11","text":" מצודת ציון  מחשים. משתיקים כמו עת לחשות (קהלת ג') ","titles":[{"title":"נחמיה ח יא"},{"title":"נחמיה פרק ח פסוק יא"}],"sefer":"tanach-37","parasha":"parasha-1","perek":"tanach-37-8","positionInPerek":11,"positionInParasha":160},{"uri":"tanach-metzudattzion-37-8-14","text":" מצודת ציון  ויעבירו קול. הוא ענין הכרזה כמו ויעבירו קול במחנה (שמות ל''ו) ","titles":[{"title":"נחמיה ח יד"},{"title":"נחמיה פרק ח פסוק יד"}],"sefer":"tanach-37","parasha":"parasha-1","perek":"tanach-37-8","positionInPerek":14,"positionInParasha":163},{"uri":"tanach-metzudattzion-37-9-9","text":" מצודת ציון  עני. מלשון עינוי ","titles":[{"title":"נחמיה ט ט"},{"title":"נחמיה פרק ט פסוק ט"}],"sefer":"tanach-37","parasha":"parasha-1","perek":"tanach-37-9","positionInPerek":9,"positionInParasha":174},{"uri":"tanach-metzudattzion-37-9-11","text":" מצודת ציון  בקעת. חלקת לשנים ","titles":[{"title":"נחמיה ט יא"},{"title":"נחמיה פרק ט פסוק יא"}],"sefer":"tanach-37","parasha":"parasha-1","perek":"tanach-37-9","positionInPerek":11,"positionInParasha":176},{"uri":"tanach-metzudattzion-37-9-12","text":" מצודת ציון  הנחיתם. הנהגתם כמו ולא נחם (שמות י''ג) ","titles":[{"title":"נחמיה ט יב"},{"title":"נחמיה פרק ט פסוק יב"}],"sefer":"tanach-37","parasha":"parasha-1","perek":"tanach-37-9","positionInPerek":12,"positionInParasha":177},{"uri":"tanach-metzudattzion-37-9-16","text":" מצודת ציון  ערפם. הוא מול הפנים ","titles":[{"title":"נחמיה ט טז"},{"title":"נחמיה פרק ט פסוק טז"}],"sefer":"tanach-37","parasha":"parasha-1","perek":"tanach-37-9","positionInPerek":16,"positionInParasha":181},{"uri":"tanach-metzudattzion-37-9-17","text":" מצודת ציון  וימאנו. מלשון מיאון וסירוב ","titles":[{"title":"נחמיה ט יז"},{"title":"נחמיה פרק ט פסוק יז"}],"sefer":"tanach-37","parasha":"parasha-1","perek":"tanach-37-9","positionInPerek":17,"positionInParasha":182},{"uri":"tanach-metzudattzion-37-9-18","text":" מצודת ציון  מסכה. מדבר הניצק וניתך ","titles":[{"title":"נחמיה ט יח"},{"title":"נחמיה פרק ט פסוק יח"}],"sefer":"tanach-37","parasha":"parasha-1","perek":"tanach-37-9","positionInPerek":18,"positionInParasha":183},{"uri":"tanach-metzudattzion-37-9-20","text":" מצודת ציון  ומנך. מלשון מן ","titles":[{"title":"נחמיה ט כ"},{"title":"נחמיה פרק ט פסוק כ"}],"sefer":"tanach-37","parasha":"parasha-1","perek":"tanach-37-9","positionInPerek":20,"positionInParasha":185},{"uri":"tanach-metzudattzion-37-9-21","text":" מצודת ציון  כלכלתם. ענין ספוק הצורך כמו ויכלכל יוסף (בראשית מ''ז) ","titles":[{"title":"נחמיה ט כא"},{"title":"נחמיה פרק ט פסוק כא"}],"sefer":"tanach-37","parasha":"parasha-1","perek":"tanach-37-9","positionInPerek":21,"positionInParasha":186},{"uri":"tanach-metzudattzion-37-9-22","text":" מצודת ציון  לפאה. לקצה כמו פאת שדך (ויקרא י''ט) ","titles":[{"title":"נחמיה ט כב"},{"title":"נחמיה פרק ט פסוק כב"}],"sefer":"tanach-37","parasha":"parasha-1","perek":"tanach-37-9","positionInPerek":22,"positionInParasha":187},{"uri":"tanach-metzudattzion-37-9-24","text":" מצודת ציון  ותכנע. מלשון הכנעה ","titles":[{"title":"נחמיה ט כד"},{"title":"נחמיה פרק ט פסוק כד"}],"sefer":"tanach-37","parasha":"parasha-1","perek":"tanach-37-9","positionInPerek":24,"positionInParasha":189},{"uri":"tanach-metzudattzion-37-9-25","text":" מצודת ציון  בצורות. מלשון מבצר ","titles":[{"title":"נחמיה ט כה"},{"title":"נחמיה פרק ט פסוק כה"}],"sefer":"tanach-37","parasha":"parasha-1","perek":"tanach-37-9","positionInPerek":25,"positionInParasha":190},{"uri":"tanach-metzudattzion-37-9-26","text":" מצודת ציון  גום. גופם כמו גוית שאול (שמואל א' ל''א) ","titles":[{"title":"נחמיה ט כו"},{"title":"נחמיה פרק ט פסוק כו"}],"sefer":"tanach-37","parasha":"parasha-1","perek":"tanach-37-9","positionInPerek":26,"positionInParasha":191},{"uri":"tanach-metzudattzion-37-9-27","text":" מצודת ציון  ויצרו. מלשון צרה ","titles":[{"title":"נחמיה ט כז"},{"title":"נחמיה פרק ט פסוק כז"}],"sefer":"tanach-37","parasha":"parasha-1","perek":"tanach-37-9","positionInPerek":27,"positionInParasha":192},{"uri":"tanach-metzudattzion-37-9-28","text":" מצודת ציון  וירדו. ומשלו כמו רדה בקרב אויביך (תהלים ק''י) ","titles":[{"title":"נחמיה ט כח"},{"title":"נחמיה פרק ט פסוק כח"}],"sefer":"tanach-37","parasha":"parasha-1","perek":"tanach-37-9","positionInPerek":28,"positionInParasha":193},{"uri":"tanach-metzudattzion-37-9-29","text":" מצודת ציון  ותעד. ענין התראה ","titles":[{"title":"נחמיה ט כט"},{"title":"נחמיה פרק ט פסוק כט"}],"sefer":"tanach-37","parasha":"parasha-1","perek":"tanach-37-9","positionInPerek":29,"positionInParasha":194},{"uri":"tanach-metzudattzion-37-9-32","text":" מצודת ציון  התלאה. ענין יגיעה וטורח כמו את כל התלאה (שמות י''ח) ","titles":[{"title":"נחמיה ט לב"},{"title":"נחמיה פרק ט פסוק לב"}],"sefer":"tanach-37","parasha":"parasha-1","perek":"tanach-37-9","positionInPerek":32,"positionInParasha":197},{"uri":"tanach-metzudattzion-37-9-35","text":" מצודת ציון  ממעלליהם. ממעשיהם כמו עולל לי (איכה א') ","titles":[{"title":"נחמיה ט לה"},{"title":"נחמיה פרק ט פסוק לה"}],"sefer":"tanach-37","parasha":"parasha-1","perek":"tanach-37-9","positionInPerek":35,"positionInParasha":200},{"uri":"tanach-metzudattzion-37-9-37","text":" מצודת ציון  גויותינו. ענין גוף ","titles":[{"title":"נחמיה ט לז"},{"title":"נחמיה פרק ט פסוק לז"}],"sefer":"tanach-37","parasha":"parasha-1","perek":"tanach-37-9","positionInPerek":37,"positionInParasha":202},{"uri":"tanach-metzudattzion-37-10-1","text":" מצודת ציון  אמנה. ענין קיום כמו יאמן נא דברך (מ''א ה') ","titles":[{"title":"נחמיה י א"},{"title":"נחמיה פרק י פסוק א"}],"sefer":"tanach-37","parasha":"parasha-1","perek":"tanach-37-10","positionInPerek":1,"positionInParasha":203},{"uri":"tanach-metzudattzion-37-10-8","text":" מצודת ציון  באלה. הוא קללת השבועה כמו בשבועת האלה (במדבר ה') ","titles":[{"title":"נחמיה י ל"},{"title":"נחמיה פרק י פסוק ל"}],"sefer":"tanach-37","parasha":"parasha-1","perek":"tanach-37-10","positionInPerek":8,"positionInParasha":210},{"uri":"tanach-metzudattzion-37-10-10","text":" מצודת ציון  ונטש. ונעזוב כמו תשמטנה ונטשתה (שמות כ''ג) ","titles":[{"title":"נחמיה י לב"},{"title":"נחמיה פרק י פסוק לב"}],"sefer":"tanach-37","parasha":"parasha-1","perek":"tanach-37-10","positionInPerek":10,"positionInParasha":212},{"uri":"tanach-metzudattzion-37-10-12","text":" מצודת ציון  המערכת. ענין סדור ","titles":[{"title":"נחמיה י לד"},{"title":"נחמיה פרק י פסוק לד"}],"sefer":"tanach-37","parasha":"parasha-1","perek":"tanach-37-10","positionInPerek":12,"positionInParasha":214},{"uri":"tanach-metzudattzion-37-10-13","text":" מצודת ציון  מזומנים. ענין הכנה וקביעות וכן בעתים מזומנות (לקמן י''ג) ","titles":[{"title":"נחמיה י לה"},{"title":"נחמיה פרק י פסוק לה"}],"sefer":"tanach-37","parasha":"parasha-1","perek":"tanach-37-10","positionInPerek":13,"positionInParasha":215},{"uri":"tanach-metzudattzion-37-10-16","text":" מצודת ציון  עריסותינו. ענין עיסה כמו ראשית עריסותיכם (במדבר ט''ו) ","titles":[{"title":"נחמיה י לח"},{"title":"נחמיה פרק י פסוק לח"}],"sefer":"tanach-37","parasha":"parasha-1","perek":"tanach-37-10","positionInPerek":16,"positionInParasha":218},{"uri":"tanach-metzudattzion-37-11-1","text":" מצודת ציון  הידות. החלקים כמו וארבע הידות (בראשית מ''ז) ","titles":[{"title":"נחמיה יא א"},{"title":"נחמיה פרק יא פסוק א"}],"sefer":"tanach-37","parasha":"parasha-1","perek":"tanach-37-11","positionInPerek":1,"positionInParasha":221},{"uri":"tanach-metzudattzion-37-11-16","text":" מצודת ציון  יהודה. מלשון הודות והלל ","titles":[{"title":"נחמיה יא יז"},{"title":"נחמיה פרק יא פסוק יז"}],"sefer":"tanach-37","parasha":"parasha-1","perek":"tanach-37-11","positionInPerek":16,"positionInParasha":236},{"uri":"tanach-metzudattzion-37-11-21","text":" מצודת ציון  ואמנה. ענין קיום ","titles":[{"title":"נחמיה יא כג"},{"title":"נחמיה פרק יא פסוק כג"}],"sefer":"tanach-37","parasha":"parasha-1","perek":"tanach-37-11","positionInPerek":21,"positionInParasha":241},{"uri":"tanach-metzudattzion-37-12-3","text":" מצודת ציון  הידות. מלשון הודות והלול ","titles":[{"title":"נחמיה יב ח"},{"title":"נחמיה פרק יב פסוק ח"}],"sefer":"tanach-37","parasha":"parasha-1","perek":"tanach-37-12","positionInPerek":3,"positionInParasha":249},{"uri":"tanach-metzudattzion-37-12-15","text":" מצודת ציון  הפחה. המושל ","titles":[{"title":"נחמיה יב כו"},{"title":"נחמיה פרק יב פסוק כו"}],"sefer":"tanach-37","parasha":"parasha-1","perek":"tanach-37-12","positionInPerek":15,"positionInParasha":261},{"uri":"tanach-metzudattzion-37-12-16","text":" מצודת ציון  ובחנוכת. התחלת דבר מה לעמוד בה משם והלאה קרוי חנוך בל' מקרא ","titles":[{"title":"נחמיה יב כז"},{"title":"נחמיה פרק יב פסוק כז"}],"sefer":"tanach-37","parasha":"parasha-1","perek":"tanach-37-12","positionInPerek":16,"positionInParasha":262},{"uri":"tanach-metzudattzion-37-12-17","text":" מצודת ציון  הככר. המישור ","titles":[{"title":"נחמיה יב כח"},{"title":"נחמיה פרק יב פסוק כח"}],"sefer":"tanach-37","parasha":"parasha-1","perek":"tanach-37-12","positionInPerek":17,"positionInParasha":263},{"uri":"tanach-metzudattzion-37-12-26","text":" מצודת ציון  ועל, מעל. ענינם כמו לפני ואצל ","titles":[{"title":"נחמיה יב לז"},{"title":"נחמיה פרק יב פסוק לז"}],"sefer":"tanach-37","parasha":"parasha-1","perek":"tanach-37-12","positionInPerek":26,"positionInParasha":272},{"uri":"tanach-metzudattzion-37-12-33","text":" מצודת ציון  הנשכות. כמו הלשכות ","titles":[{"title":"נחמיה יב מד"},{"title":"נחמיה פרק יב פסוק מד"}],"sefer":"tanach-37","parasha":"parasha-1","perek":"tanach-37-12","positionInPerek":33,"positionInParasha":279},{"uri":"tanach-metzudattzion-37-13-2","text":" מצודת ציון  לא קדמו. לא באו לפניהם כמו במה אקדם ה' (מיכה ו') ","titles":[{"title":"נחמיה יג ב"},{"title":"נחמיה פרק יג פסוק ב"}],"sefer":"tanach-37","parasha":"parasha-1","perek":"tanach-37-13","positionInPerek":2,"positionInParasha":284},{"uri":"tanach-metzudattzion-37-13-5","text":" מצודת ציון  ויעש. ענין תקון כמו וימהר לעשות אותו (בראשית י''ח) ","titles":[{"title":"נחמיה יג ה"},{"title":"נחמיה פרק יג פסוק ה"}],"sefer":"tanach-37","parasha":"parasha-1","perek":"tanach-37-13","positionInPerek":5,"positionInParasha":287},{"uri":"tanach-metzudattzion-37-13-6","text":" מצודת ציון  נשאלתי. מל' שאלה ובקשה ועל כי שאלתו היה על עצמו אמר בלשון נפעל וכן נשאל נשאל דוד (שמואל א' כ') ","titles":[{"title":"נחמיה יג ו"},{"title":"נחמיה פרק יג פסוק ו"}],"sefer":"tanach-37","parasha":"parasha-1","perek":"tanach-37-13","positionInPerek":6,"positionInParasha":288},{"uri":"tanach-metzudattzion-37-13-7","text":" מצודת ציון  נשכה. כמו לשכה ","titles":[{"title":"נחמיה יג ז"},{"title":"נחמיה פרק יג פסוק ז"}],"sefer":"tanach-37","parasha":"parasha-1","perek":"tanach-37-13","positionInPerek":7,"positionInParasha":289},{"uri":"tanach-metzudattzion-37-13-11","text":" מצודת ציון  ואריבה. מלשון ריב ","titles":[{"title":"נחמיה יג יא"},{"title":"נחמיה פרק יג פסוק יא"}],"sefer":"tanach-37","parasha":"parasha-1","perek":"tanach-37-13","positionInPerek":11,"positionInParasha":293},{"uri":"tanach-metzudattzion-37-13-14","text":" מצודת ציון  תמח. כמו תמחה והוא ענין מחיקה ","titles":[{"title":"נחמיה יג יד"},{"title":"נחמיה פרק יג פסוק יד"}],"sefer":"tanach-37","parasha":"parasha-1","perek":"tanach-37-13","positionInPerek":14,"positionInParasha":296},{"uri":"tanach-metzudattzion-37-13-15","text":" מצודת ציון  גתות. הכלי שדורכים בו הענבים להוציא היין קרוי גת וכן כדורך בגת (ישעיה ס''ג) ","titles":[{"title":"נחמיה יג טו"},{"title":"נחמיה פרק יג פסוק טו"}],"sefer":"tanach-37","parasha":"parasha-1","perek":"tanach-37-13","positionInPerek":15,"positionInParasha":297},{"uri":"tanach-metzudattzion-37-13-16","text":" מצודת ציון  דג. ר''ל קבוצת דגים ","titles":[{"title":"נחמיה יג טז"},{"title":"נחמיה פרק יג פסוק טז"}],"sefer":"tanach-37","parasha":"parasha-1","perek":"tanach-37-13","positionInPerek":16,"positionInParasha":298},{"uri":"tanach-metzudattzion-37-13-17","text":" מצודת ציון  חורי יהודה. שרי יהודה ","titles":[{"title":"נחמיה יג יז"},{"title":"נחמיה פרק יג פסוק יז"}],"sefer":"tanach-37","parasha":"parasha-1","perek":"tanach-37-13","positionInPerek":17,"positionInParasha":299},{"uri":"tanach-metzudattzion-37-13-19","text":" מצודת ציון  צללו. מלשון צל ","titles":[{"title":"נחמיה יג יט"},{"title":"נחמיה פרק יג פסוק יט"}],"sefer":"tanach-37","parasha":"parasha-1","perek":"tanach-37-13","positionInPerek":19,"positionInParasha":301},{"uri":"tanach-metzudattzion-37-13-20","text":" מצודת ציון  הרוכלים. מוכרי הבושם ","titles":[{"title":"נחמיה יג כ"},{"title":"נחמיה פרק יג פסוק כ"}],"sefer":"tanach-37","parasha":"parasha-1","perek":"tanach-37-13","positionInPerek":20,"positionInParasha":302},{"uri":"tanach-metzudattzion-37-13-21","text":" מצודת ציון  לנים. מל' לינה ","titles":[{"title":"נחמיה יג כא"},{"title":"נחמיה פרק יג פסוק כא"}],"sefer":"tanach-37","parasha":"parasha-1","perek":"tanach-37-13","positionInPerek":21,"positionInParasha":303},{"uri":"tanach-metzudattzion-37-13-22","text":" מצודת ציון  וחוסה. ענין חמלה כמו אתה חסת על הקיקיון (יונה ד') ","titles":[{"title":"נחמיה יג כב"},{"title":"נחמיה פרק יג פסוק כב"}],"sefer":"tanach-37","parasha":"parasha-1","perek":"tanach-37-13","positionInPerek":22,"positionInParasha":304},{"uri":"tanach-metzudattzion-37-13-25","text":" מצודת ציון  ואמרטם. ענין תלישת השער כמו ואיש כי ימרט ראשו (ויקרא י''ג) ","titles":[{"title":"נחמיה יג כה"},{"title":"נחמיה פרק יג פסוק כה"}],"sefer":"tanach-37","parasha":"parasha-1","perek":"tanach-37-13","positionInPerek":25,"positionInParasha":307},{"uri":"tanach-metzudattzion-37-13-27","text":" מצודת ציון  למעול. ענין חטא ופשע ","titles":[{"title":"נחמיה יג כז"},{"title":"נחמיה פרק יג פסוק כז"}],"sefer":"tanach-37","parasha":"parasha-1","perek":"tanach-37-13","positionInPerek":27,"positionInParasha":309},{"uri":"tanach-metzudattzion-37-13-29","text":" מצודת ציון  גאלי. ענין טנוף ומאוס כמו ויגאלו מן הכהונה (לעיל ז') ","titles":[{"title":"נחמיה יג כט"},{"title":"נחמיה פרק יג פסוק כט"}],"sefer":"tanach-37","parasha":"parasha-1","perek":"tanach-37-13","positionInPerek":29,"positionInParasha":311},{"uri":"tanach-metzudattzion-37-13-30","text":" מצודת ציון  משמרות. כל דבר המוטל על אנשים הרבה לעשות כל אחד בזמנו קרוי משמר כי ישמור לבוא בזמן הקבוע לו ולא יעבור ","titles":[{"title":"נחמיה יג ל"},{"title":"נחמיה פרק יג פסוק ל"}],"sefer":"tanach-37","parasha":"parasha-1","perek":"tanach-37-13","positionInPerek":30,"positionInParasha":312},{"uri":"tanach-metzudattzion-37-13-31","text":" מצודת ציון  מזומנות. ענין הכנה וקביעות כמו לעתים מזומנים (לעיל י') ","titles":[{"title":"נחמיה יג לא"},{"title":"נחמיה פרק יג פסוק לא"}],"sefer":"tanach-37","parasha":"parasha-1","perek":"tanach-37-13","positionInPerek":31,"positionInParasha":313}]}